{
    "/js/app.js": "/js/app.js?id=048ddd423ba0913a9fe7",
    "/css/style.css": "/css/style.css?id=9629705facc28be81891",
    "/fonts/FontAwesome.otf": "/fonts/FontAwesome.otf?id=663236d7aa447620b641",
    "/fonts/Simple-Line-Icons.eot": "/fonts/Simple-Line-Icons.eot?id=c7355491cc189d855476",
    "/fonts/Simple-Line-Icons.svg": "/fonts/Simple-Line-Icons.svg?id=00ce23caac2c875bcc6d",
    "/fonts/Simple-Line-Icons.ttf": "/fonts/Simple-Line-Icons.ttf?id=a9f42adb0cb6c022926b",
    "/fonts/Simple-Line-Icons.woff": "/fonts/Simple-Line-Icons.woff?id=cd60894e3c8701413f42",
    "/fonts/Simple-Line-Icons.woff2": "/fonts/Simple-Line-Icons.woff2?id=7fd444d103f5b5e5bb33",
    "/fonts/fontawesome-webfont.eot": "/fonts/fontawesome-webfont.eot?id=016fa45033a942ffecad",
    "/fonts/fontawesome-webfont.svg": "/fonts/fontawesome-webfont.svg?id=912ec66d7572ff821749",
    "/fonts/fontawesome-webfont.ttf": "/fonts/fontawesome-webfont.ttf?id=ecebce3ab95b6640919b",
    "/fonts/fontawesome-webfont.woff": "/fonts/fontawesome-webfont.woff?id=5e0388aeae16469773b8",
    "/fonts/fontawesome-webfont.woff2": "/fonts/fontawesome-webfont.woff2?id=d829b32251e423806ca9"
}
